CHANGELOG.rst
LICENSE.txt
MANIFEST.in
README.rst
requirements.txt
setup.cfg
setup.py
scine_parrot/__init__.py
scine_parrot/__main__.py
scine_parrot/_version.py
scine_parrot/ani_calculator.py
scine_parrot/calculator.py
scine_parrot/lmlp.py
scine_parrot/lmlp_calculator.py
scine_parrot/m3gnet_calculator.py
scine_parrot/mace_calculator.py
scine_parrot/module.py
scine_parrot.egg-info/PKG-INFO
scine_parrot.egg-info/SOURCES.txt
scine_parrot.egg-info/dependency_links.txt
scine_parrot.egg-info/entry_points.txt
scine_parrot.egg-info/not-zip-safe
scine_parrot.egg-info/requires.txt
scine_parrot.egg-info/top_level.txt
scine_parrot/resources/__init__.py
scine_parrot/resources/lmlp/lMLP-SN2.ini
scine_parrot/resources/lmlp/lMLP-SN2.pt
scine_parrot/test/__init__.py
scine_parrot/test/test_ani_calculator.py
scine_parrot/test/test_lmlp.py
scine_parrot/test/test_lmlp_calculator.py
scine_parrot/test/test_m3gnet_calculator.py
scine_parrot/test/test_mace_calculator.py
scine_parrot/test/resources/__init__.py